{
    "nodes": [
        {
            "id": 4,
            "is_leaf": true,
            "survival": 10,
            "not_survival": 49
        },
        {
            "id": 5,
            "is_leaf": true,
            "survival": 19,
            "not_survival": 22
        },
        {
            "id": 3,
            "is_leaf": false,
            "attribute": "Age",
            "is_categorical": false,
            "value": 6.9621
        },
        {
            "id": 7,
            "is_leaf": true,
            "survival": 5,
            "not_survival": 68
        },
        {
            "id": 8,
            "is_leaf": true,
            "survival": 66,
            "not_survival": 425
        },
        {
            "id": 6,
            "is_leaf": false,
            "attribute": "Age",
            "is_categorical": false,
            "value": 38.8061
        },
        {
            "id": 2,
            "is_leaf": false,
            "attribute": "Parents / Children aboard",
            "is_categorical": false,
            "value": 0.1674
        },
        {
            "id": 10,
            "is_leaf": true,
            "survival": 2,
            "not_survival": 0
        },
        {
            "id": 12,
            "is_leaf": true,
            "survival": 1,
            "not_survival": 11
        },
        {
            "id": 13,
            "is_leaf": true,
            "survival": 58,
            "not_survival": 107
        },
        {
            "id": 11,
            "is_leaf": false,
            "attribute": "Fare",
            "is_categorical": false,
            "value": 205.3479
        },
        {
            "id": 9,
            "is_leaf": false,
            "attribute": "Fare",
            "is_categorical": false,
            "value": 339.7015
        },
        {
            "id": 1,
            "is_leaf": false,
            "attribute": "Class",
            "is_categorical": false,
            "value": 1.9775
        },
        {
            "id": 17,
            "is_leaf": true,
            "survival": 12,
            "not_survival": 33
        },
        {
            "id": 18,
            "is_leaf": true,
            "survival": 94,
            "not_survival": 77
        },
        {
            "id": 16,
            "is_leaf": false,
            "attribute": "Fare",
            "is_categorical": false,
            "value": 20.2629
        },
        {
            "id": 20,
            "is_leaf": true,
            "survival": 21,
            "not_survival": 0
        },
        {
            "id": 21,
            "is_leaf": true,
            "survival": 73,
            "not_survival": 12
        },
        {
            "id": 19,
            "is_leaf": false,
            "attribute": "Parents / Children aboard",
            "is_categorical": false,
            "value": 1.952
        },
        {
            "id": 15,
            "is_leaf": false,
            "attribute": "Class",
            "is_categorical": false,
            "value": 2.2462
        },
        {
            "id": 24,
            "is_leaf": true,
            "survival": 36,
            "not_survival": 3
        },
        {
            "id": 25,
            "is_leaf": true,
            "survival": 88,
            "not_survival": 0
        },
        {
            "id": 23,
            "is_leaf": false,
            "attribute": "Fare",
            "is_categorical": false,
            "value": 135.0008
        },
        {
            "id": 27,
            "is_leaf": true,
            "survival": 6,
            "not_survival": 2
        },
        {
            "id": 28,
            "is_leaf": true,
            "survival": 9,
            "not_survival": 0
        },
        {
            "id": 26,
            "is_leaf": false,
            "attribute": "Port of Embarkation",
            "is_categorical": true,
            "value": [
                "Southampton"
            ]
        },
        {
            "id": 22,
            "is_leaf": false,
            "attribute": "Fare",
            "is_categorical": false,
            "value": 34.0568
        },
        {
            "id": 14,
            "is_leaf": false,
            "attribute": "Class",
            "is_categorical": false,
            "value": 1.3525
        },
        {
            "id": 0,
            "is_leaf": false,
            "attribute": "Gender",
            "is_categorical": true,
            "value": [
                "female"
            ]
        }
    ],
    "links": [
        {
            "source": 3,
            "target": 5,
            "direction": "left"
        },
        {
            "source": 3,
            "target": 4,
            "direction": "right"
        },
        {
            "source": 6,
            "target": 8,
            "direction": "left"
        },
        {
            "source": 6,
            "target": 7,
            "direction": "right"
        },
        {
            "source": 2,
            "target": 6,
            "direction": "left"
        },
        {
            "source": 2,
            "target": 3,
            "direction": "right"
        },
        {
            "source": 11,
            "target": 13,
            "direction": "left"
        },
        {
            "source": 11,
            "target": 12,
            "direction": "right"
        },
        {
            "source": 9,
            "target": 11,
            "direction": "left"
        },
        {
            "source": 9,
            "target": 10,
            "direction": "right"
        },
        {
            "source": 1,
            "target": 9,
            "direction": "left"
        },
        {
            "source": 1,
            "target": 2,
            "direction": "right"
        },
        {
            "source": 16,
            "target": 18,
            "direction": "left"
        },
        {
            "source": 16,
            "target": 17,
            "direction": "right"
        },
        {
            "source": 19,
            "target": 21,
            "direction": "left"
        },
        {
            "source": 19,
            "target": 20,
            "direction": "right"
        },
        {
            "source": 15,
            "target": 19,
            "direction": "left"
        },
        {
            "source": 15,
            "target": 16,
            "direction": "right"
        },
        {
            "source": 23,
            "target": 25,
            "direction": "left"
        },
        {
            "source": 23,
            "target": 24,
            "direction": "right"
        },
        {
            "source": 26,
            "target": 28,
            "direction": "left"
        },
        {
            "source": 26,
            "target": 27,
            "direction": "right"
        },
        {
            "source": 22,
            "target": 26,
            "direction": "left"
        },
        {
            "source": 22,
            "target": 23,
            "direction": "right"
        },
        {
            "source": 14,
            "target": 22,
            "direction": "left"
        },
        {
            "source": 14,
            "target": 15,
            "direction": "right"
        },
        {
            "source": 0,
            "target": 14,
            "direction": "left"
        },
        {
            "source": 0,
            "target": 1,
            "direction": "right"
        }
    ]
}
